[
  {
    "description": "    Eu como usuário do sistema\n    Desejo realizar o cadastro de novos usuários\n    Para que seja possível armazenar e gerenciar seus dados",
    "keyword": "Feature",
    "name": "Login",
    "line": 1,
    "id": "login",
    "tags": [],
    "uri": "login.feature",
    "elements": [
      {
        "id": "login;realizar-cadastro-com-credenciais-válidas",
        "keyword": "Scenario",
        "line": 9,
        "name": "Realizar cadastro com credenciais válidas",
        "tags": [],
        "type": "scenario",
        "steps": [
          {
            "arguments": [],
            "keyword": "Given ",
            "line": 7,
            "name": "que eu acesso a página",
            "result": {
              "status": "passed",
              "duration": 315000000
            }
          },
          {
            "arguments": [],
            "keyword": "When ",
            "line": 10,
            "name": "eu insiro todos os meus dados corretamente",
            "result": {
              "status": "passed",
              "duration": 971000000
            }
          },
          {
            "arguments": [],
            "keyword": "And ",
            "line": 11,
            "name": "clico no botão Cadastrar",
            "result": {
              "status": "passed",
              "duration": 91000000
            }
          },
          {
            "arguments": [],
            "keyword": "Then ",
            "line": 12,
            "name": "meu cadastro é feito com sucesso",
            "result": {
              "status": "passed",
              "duration": 14000000
            }
          }
        ]
      },
      {
        "id": "login;realizar-cadastro-com-credenciais-inválidas",
        "keyword": "Scenario",
        "line": 14,
        "name": "Realizar cadastro com credenciais inválidas",
        "tags": [],
        "type": "scenario",
        "steps": [
          {
            "arguments": [],
            "keyword": "Given ",
            "line": 7,
            "name": "que eu acesso a página",
            "result": {
              "status": "passed",
              "duration": 242000000
            }
          },
          {
            "arguments": [],
            "keyword": "When ",
            "line": 15,
            "name": "eu insiro dados inválidos",
            "result": {
              "status": "passed",
              "duration": 698000000
            }
          },
          {
            "arguments": [],
            "keyword": "And ",
            "line": 16,
            "name": "clico no botão Cadastrar",
            "result": {
              "status": "passed",
              "duration": 91000000
            }
          },
          {
            "arguments": [],
            "keyword": "Then ",
            "line": 17,
            "name": "meu cadastro não é realizado",
            "result": {
              "status": "passed",
              "duration": 51000000
            }
          }
        ]
      },
      {
        "id": "login;realizar-cadastro-sem-credenciais",
        "keyword": "Scenario",
        "line": 19,
        "name": "Realizar cadastro sem credenciais",
        "tags": [],
        "type": "scenario",
        "steps": [
          {
            "arguments": [],
            "keyword": "Given ",
            "line": 7,
            "name": "que eu acesso a página",
            "result": {
              "status": "passed",
              "duration": 240000000
            }
          },
          {
            "arguments": [],
            "keyword": "When ",
            "line": 20,
            "name": "eu clico no botão Cadastrar sem inserir nenhum dado",
            "result": {
              "status": "passed",
              "duration": 93000000
            }
          },
          {
            "arguments": [],
            "keyword": "Then ",
            "line": 21,
            "name": "meu cadastro não é finalizado",
            "result": {
              "status": "passed",
              "duration": 39000000
            }
          }
        ]
      }
    ]
  }
]